.DS_Store
depair/__init__.py
depair/eval.py
depair-0.0.2.dist-info/LICENSE
depair-0.0.2.dist-info/METADATA
depair-0.0.2.dist-info/WHEEL
depair-0.0.2.dist-info/top_level.txt
depair-0.0.2.dist-info/RECORD
