Metadata-Version: 2.1
Name: depair
Version: 0.0.2
Summary: A scanpy-based single-cell crosstalk analysis package
Home-page: https://github.com/chansigit/depair
Author: Sijie Chen
Author-email: chansigit@gmail.com
Classifier: Programming Language :: Python :: 3
Classifier: License :: OSI Approved :: MIT License
Classifier: Operating System :: OS Independent
License-File: LICENSE
